spacedock/__init__.py
spacedock-0.0.1.dist-info/LICENSE
spacedock-0.0.1.dist-info/METADATA
spacedock-0.0.1.dist-info/WHEEL
spacedock-0.0.1.dist-info/entry_points.txt
spacedock-0.0.1.dist-info/RECORD
